conlog/Console.py
conlog/__init__.py
conlog/disabled.py
conlog/expr_debug.py
conlog/formats.py
conlog/impl.py
tests/EnvVar.py
tests/TimeTools.py
tests/__init__.py
tests/test_class.py
tests/test_cls.py
tests/test_enabled.py
tests/test_fngrp.py
tests/test_static.py
con_log-1.0.7.dist-info/LICENSE-MIT
con_log-1.0.7.dist-info/METADATA
con_log-1.0.7.dist-info/WHEEL
con_log-1.0.7.dist-info/top_level.txt
con_log-1.0.7.dist-info/RECORD
